spurplus/__init__.py
spurplus/py.typed
spurplus/sftp.py
spurplus-2.3.5.dist-info/LICENSE.txt
spurplus-2.3.5.dist-info/METADATA
spurplus-2.3.5.dist-info/WHEEL
spurplus-2.3.5.dist-info/top_level.txt
spurplus-2.3.5.dist-info/RECORD
