Metadata-Version: 2.1
Name: spurplus
Version: 2.3.5
Summary: Manage remote machines and file operations over SSH.
Home-page: http://github.com/Parquery/spurplus
Author: Marko Ristin
Author-email: marko.ristin@gmail.com
License: License :: OSI Approved :: MIT License
Keywords: ssh sftp spur paramiko execute remote commands modify files
Classifier: Development Status :: 5 - Production/Stable
Classifier: Intended Audience :: Developers
Classifier: License :: OSI Approved :: MIT License
Classifier: Programming Language :: Python :: 3.5
Classifier: Programming Language :: Python :: 3.6
Classifier: Programming Language :: Python :: 3.7
Classifier: Programming Language :: Python :: 3.8
License-File: LICENSE.txt
Requires-Dist: spur ==0.3.23
Requires-Dist: typing-extensions >=3.6.2.1
Requires-Dist: icontract <3,>=2.0.1
Requires-Dist: temppathlib <2,>=1.0.3
Provides-Extra: dev
Requires-Dist: mypy ==0.790 ; extra == 'dev'
Requires-Dist: pylint ==2.6.0 ; extra == 'dev'
Requires-Dist: yapf ==0.20.2 ; extra == 'dev'
Requires-Dist: tox >=3.0.0 ; extra == 'dev'
Requires-Dist: coverage <5,>=4.5.1 ; extra == 'dev'
Requires-Dist: pydocstyle <3,>=2.1.1 ; extra == 'dev'
